{"nodes": [{"id": "clippings_how_to_measure_prompt_level_visibility_in_ai_search_document", "label": "How to Measure Prompt-Level Visibility in AI Search", "file_type": "document", "source_file": "Clippings/How to measure prompt-level visibility in AI search.md", "source_location": null, "source_url": "https://searchengineland.com/measure-prompt-level-visibility-ai-search-481577", "captured_at": "2026-07-07", "author": "Casey Nifong", "contributor": null}, {"id": "clippings_how_to_measure_prompt_level_visibility_in_ai_search_inclusion_rate_metric", "label": "Inclusion Rate Metric", "file_type": "concept", "source_file": "Clippings/How to measure prompt-level visibility in AI search.md", "source_location": "### Inclusion rate", "source_url": "https://searchengineland.com/measure-prompt-level-visibility-ai-search-481577", "captured_at": "2026-07-07", "author": "Casey Nifong", "contributor": null}, {"id": "clippings_how_to_measure_prompt_level_visibility_in_ai_search_prompt_library_framework", "label": "Prompt Library Framework (vs Keyword List)", "file_type": "concept", "source_file": "Clippings/How to measure prompt-level visibility in AI search.md", "source_location": "### 2. Build a prompt library instead of a keyword list", "source_url": "https://searchengineland.com/measure-prompt-level-visibility-ai-search-481577", "captured_at": "2026-07-07", "author": "Casey Nifong", "contributor": null}, {"id": "clippings_how_to_measure_prompt_level_visibility_in_ai_search_5_step_ai_visibility_framework", "label": "5-Step Framework for Tracking AI Visibility", "file_type": "rationale", "rationale": "AI search visibility is probabilistic, not deterministic (no 'position 1'), so measurement should shift from rank-tracking to prompt-cluster inclusion rate, multi-turn conversation coverage, and framing/sentiment, since no platform exposes every AI conversation.", "source_file": "Clippings/How to measure prompt-level visibility in AI search.md", "source_location": "## A 5-step framework for tracking AI visibility", "source_url": "https://searchengineland.com/measure-prompt-level-visibility-ai-search-481577", "captured_at": "2026-07-07", "author": "Casey Nifong", "contributor": null}, {"id": "clippings_how_to_measure_prompt_level_visibility_in_ai_search_competitive_share_of_voice", "label": "Competitive Share of Voice Metric", "file_type": "concept", "source_file": "Clippings/How to measure prompt-level visibility in AI search.md", "source_location": "### Competitive share of voice", "source_url": "https://searchengineland.com/measure-prompt-level-visibility-ai-search-481577", "captured_at": "2026-07-07", "author": "Casey Nifong", "contributor": null}, {"id": "clippings_how_to_measure_prompt_level_visibility_in_ai_search_prompt_clusters", "label": "Prompt Clusters (Category / Industry / Feature)", "file_type": "concept", "source_file": "Clippings/How to measure prompt-level visibility in AI search.md", "source_location": "### 3. Use prompt clusters, not individual questions", "source_url": "https://searchengineland.com/measure-prompt-level-visibility-ai-search-481577", "captured_at": "2026-07-07", "author": "Casey Nifong", "contributor": null}], "edges": [{"source": "clippings_how_to_measure_prompt_level_visibility_in_ai_search_inclusion_rate_metric", "target": "clippings_how_to_measure_prompt_level_visibility_in_ai_search_5_step_ai_visibility_framework", "relation": "conceptually_related_to", "confidence": "EXTRACTED", "confidence_score": 1.0, "source_file": "Clippings/How to measure prompt-level visibility in AI search.md", "source_location": "## Metrics that actually matter", "weight": 1.0}, {"source": "clippings_how_to_measure_prompt_level_visibility_in_ai_search_competitive_share_of_voice", "target": "clippings_how_to_measure_prompt_level_visibility_in_ai_search_5_step_ai_visibility_framework", "relation": "conceptually_related_to", "confidence": "EXTRACTED", "confidence_score": 1.0, "source_file": "Clippings/How to measure prompt-level visibility in AI search.md", "source_location": "## Metrics that actually matter", "weight": 1.0}, {"source": "clippings_how_to_measure_prompt_level_visibility_in_ai_search_prompt_library_framework", "target": "clippings_how_to_measure_prompt_level_visibility_in_ai_search_prompt_clusters", "relation": "conceptually_related_to", "confidence": "EXTRACTED", "confidence_score": 1.0, "source_file": "Clippings/How to measure prompt-level visibility in AI search.md", "source_location": "### 3. Use prompt clusters, not individual questions", "weight": 1.0}, {"source": "clippings_how_to_measure_prompt_level_visibility_in_ai_search_document", "target": "marketing_defending_branded_search_from_competitor_google_ads_tactics_document", "relation": "semantically_similar_to", "confidence": "INFERRED", "confidence_score": 0.65, "source_file": "Clippings/How to measure prompt-level visibility in AI search.md", "source_location": null, "weight": 1.0}, {"source": "clippings_how_to_measure_prompt_level_visibility_in_ai_search_document", "target": "marketing_marketing_overview_document", "relation": "semantically_similar_to", "confidence": "INFERRED", "confidence_score": 0.65, "source_file": "Clippings/How to measure prompt-level visibility in AI search.md", "source_location": null, "weight": 1.0}], "hyperedges": []}